{
  "offers": [
    {
      "id": "RevU",
      "title": "RevU",
      "payout": "Varies",
      "imageUrl": "https://encrypted-tbn0.gstatic.com/images?q=tbn:ANd9GcTtGRbTPeReGKclEbElOuC9Gngy4-WjLlwEdQ&s",
      "clickUrl": "https://publishers.revenueuniverse.com/wallresp/1481/offers?uid={UID}&sid3={SID3}",
      "provider": "RevU",
      "isWall": false,
      "priority": 1,
      "devices": ["android", "ios", "windows", "mac"],
      "status": "null",
      "objectives": [
        { "name": "Open the RevU Offerwall and start earning!", "reward": "Varies" }
      ],
      "disclaimer": "All offers on RevU are handled by RevU. If you face any issues, please contact their support."
    }
  ]
}
